compyl/__init__.py
compyl/lexer.py
compyl/parser.py
compyl/__lexer/__init__.py
compyl/__lexer/errors.py
compyl/__lexer/finite_automaton.py
compyl/__lexer/interval_operations.py
compyl/__lexer/metaclass.py
compyl/__lexer/regexp.py
compyl/__parser/__init__.py
compyl/__parser/error.py
compyl/__parser/finite_automaton.py
compyl/__parser/grammar_error.py
compyl/__parser/metaclass.py
compyl/__parser/rule_formatter.py
compyl-0.2.1.dist-info/METADATA
compyl-0.2.1.dist-info/RECORD
compyl-0.2.1.dist-info/WHEEL
compyl-0.2.1.dist-info/top_level.txt
