Metadata-Version: 2.1
Name: compyl
Version: 0.2.1
Summary: Python lexing-parsing tool
Home-page: https://github.com/omelancon/ComPyl
Author: Olivier Melancon
Author-email: ol.melancon@gmail.com
License: UNKNOWN
Download-URL: https://github.com/omelancon/ComPyl/archive/v0.2.1.tar.gz
Keywords: lexer lexing parser parsing compiler
Platform: UNKNOWN
Classifier: Development Status :: 4 - Beta
Classifier: Programming Language :: Python :: 3 :: Only
Classifier: Topic :: Software Development :: Compilers
Classifier: License :: OSI Approved :: MIT License
Classifier: Intended Audience :: Developers
Requires-Dist: dill
